dotissue.py
setup.py
dotissue.egg-info/PKG-INFO
dotissue.egg-info/SOURCES.txt
dotissue.egg-info/dependency_links.txt
dotissue.egg-info/entry_points.txt
dotissue.egg-info/top_level.txt